<Properties StartupConfiguration="{E060897E-CE4A-495D-99B9-DC193E82F56E}|Default">
  <MonoDevelop.Ide.DebuggingService.Breakpoints>
    <BreakpointStore />
  </MonoDevelop.Ide.DebuggingService.Breakpoints>
  <MonoDevelop.Ide.Workspace ActiveConfiguration="Debug" />
  <MultiItemStartupConfigurations />
  <MonoDevelop.Ide.DebuggingService.PinnedWatches />
  <MonoDevelop.Ide.ItemProperties.BattleshipLite PreferredExecutionTarget="MonoDevelop.Default" />
  <MonoDevelop.Ide.Workbench ActiveDocument="BattleshipLite/Program.cs">
    <Files>
      <File FileName="BattleshipLite/Program.cs" Line="10" Column="6" />
      <File FileName="BattleshipLiteLibrary/Models/PlayerInfoModel.cs" />
      <File FileName="BattleshipLiteLibrary/GameLogic.cs" Line="49" Column="4" />
      <File FileName="BattleshipLiteLibrary/Models/GridSpotModel.cs" />
    </Files>
    <Pads>
      <Pad Id="ProjectPad">
        <State name="__root__">
          <Node name="BattleshipLiteApp" expanded="True">
            <Node name="BattleshipLite" expanded="True">
              <Node name="Program.cs" selected="True" />
            </Node>
            <Node name="BattleshipLiteLibrary" expanded="True">
              <Node name="Models" expanded="True" />
            </Node>
          </Node>
        </State>
      </Pad>
    </Pads>
  </MonoDevelop.Ide.Workbench>
</Properties>